footix/__init__.py
footix/data_io/__init__.py
footix/data_io/base_scrapper.py
footix/data_io/data_reader.py
footix/data_io/footballdata.py
footix/data_io/understat.py
footix/data_io/utils_scrapper.py
footix/implied_odds/__init__.py
footix/implied_odds/implied.py
footix/metrics/__init__.py
footix/metrics/metrics_function.py
footix/models/__init__.py
footix/models/basic_poisson.py
footix/models/bayes_xg.py
footix/models/bayesian.py
footix/models/dixon_coles.py
footix/models/elo.py
footix/models/hybrid_model.py
footix/models/score_matrix.py
footix/models/team_elo.py
footix/models/utils.py
footix/strategy/__init__.py
footix/strategy/_utils.py
footix/strategy/bets.py
footix/strategy/kelly_strategies.py
footix/strategy/portfolio_management.py
footix/strategy/select_bets.py
footix/strategy/simple.py
footix/utils/__init__.py
footix/utils/decorators.py
footix/utils/typing.py
footix/utils/utils.py
pyfootix-0.1.1.dist-info/LICENSE
pyfootix-0.1.1.dist-info/METADATA
pyfootix-0.1.1.dist-info/WHEEL
pyfootix-0.1.1.dist-info/RECORD
